light_progress/__init__.py
light_progress/core.py
light_progress/commandline/__init__.py
light_progress/commandline/progressbar.py
light_progress/commandline/widget.py
light_progress-0.7.0.0.dist-info/LICENSE.txt
light_progress-0.7.0.0.dist-info/METADATA
light_progress-0.7.0.0.dist-info/WHEEL
light_progress-0.7.0.0.dist-info/top_level.txt
light_progress-0.7.0.0.dist-info/RECORD
