Metadata-Version: 2.1
Name: light-progress
Version: 0.7.0.0
Summary: Light progress reporting tool for Python
Home-page: https://github.com/itkr/light-progress
Author: itkr
Author-email: itkrst@gmail.com
License: MIT
Platform: UNKNOWN
Classifier: Environment :: Console
Classifier: Intended Audience :: Developers
Classifier: Operating System :: OS Independent
Classifier: Programming Language :: Python
Classifier: Topic :: Utilities
License-File: LICENSE.txt
